mapof/roommates/__init__.py
mapof/roommates/cultures_.py
mapof/roommates/distances_.py
mapof/roommates/features_.py
mapof/roommates/cultures/__init__.py
mapof/roommates/cultures/_utils.py
mapof/roommates/cultures/euclidean.py
mapof/roommates/cultures/group_separable.py
mapof/roommates/cultures/impartial.py
mapof/roommates/cultures/mallows.py
mapof/roommates/cultures/urn.py
mapof/roommates/distances/__init__.py
mapof/roommates/distances/main_distances.py
mapof/roommates/features/__init__.py
mapof/roommates/features/basic_features.py
mapof/roommates/features/distance_to_stability_features.py
mapof/roommates/objects/Roommates.py
mapof/roommates/objects/RoommatesExperiment.py
mapof/roommates/objects/RoommatesFamily.py
mapof/roommates/objects/__init__.py
mapof/roommates/persistence/__init__.py
mapof/roommates/persistence/instance_exports.py
mapof/roommates/persistence/instance_imports.py
mapof_roommates-0.1.0b1.dist-info/LICENSE.txt
mapof_roommates-0.1.0b1.dist-info/METADATA
mapof_roommates-0.1.0b1.dist-info/WHEEL
mapof_roommates-0.1.0b1.dist-info/top_level.txt
mapof_roommates-0.1.0b1.dist-info/RECORD
